allennlp_dataframe_mapper/__init__.py
allennlp_dataframe_mapper/common/__init__.py
allennlp_dataframe_mapper/common/testing/__init__.py
allennlp_dataframe_mapper/common/testing/test_case.py
allennlp_dataframe_mapper/mapper.py
allennlp_dataframe_mapper/transforms/__init__.py
allennlp_dataframe_mapper/transforms/base.py
allennlp_dataframe_mapper/transforms/hash_name.py
allennlp_dataframe_mapper/transforms/preprocessing.py
allennlp_dataframe_mapper-0.3.0.dist-info/LICENSE
allennlp_dataframe_mapper-0.3.0.dist-info/WHEEL
allennlp_dataframe_mapper-0.3.0.dist-info/METADATA
allennlp_dataframe_mapper-0.3.0.dist-info/RECORD
