Metadata-Version: 2.1
Name: allennlp-dataframe-mapper
Version: 0.3.0
Summary: 
Home-page: https://github.com/shunk031/allennlp-dataframe-mapper
License: MIT
Author: Shunsuke KITADA
Author-email: shunsuke.kitada.0831@gmail.com
Requires-Python: >=3.7,<4.0
Classifier: License :: OSI Approved :: MIT License
Classifier: Programming Language :: Python :: 3
Classifier: Programming Language :: Python :: 3.10
Classifier: Programming Language :: Python :: 3.7
Classifier: Programming Language :: Python :: 3.8
Classifier: Programming Language :: Python :: 3.9
Requires-Dist: allennlp (>=2.0.0)
Requires-Dist: sklearn-pandas (>=2.0.4)
Project-URL: Repository, https://github.com/shunk031/allennlp-dataframe-mapper
